CONTRIBUTING.md
MANIFEST.in
README.rst
setup.cfg
setup.py
docs/HISTORY.txt
docs/INSTALL.txt
docs/LICENSE.GPL
docs/LICENSE.txt
eea/__init__.py
eea.pdf.egg-info/PKG-INFO
eea.pdf.egg-info/SOURCES.txt
eea.pdf.egg-info/dependency_links.txt
eea.pdf.egg-info/entry_points.txt
eea.pdf.egg-info/namespace_packages.txt
eea.pdf.egg-info/not-zip-safe
eea.pdf.egg-info/requires.txt
eea.pdf.egg-info/top_level.txt
eea/pdf/README.txt
eea/pdf/__init__.py
eea/pdf/async.py
eea/pdf/config.py
eea/pdf/configure.zcml
eea/pdf/interfaces.py
eea/pdf/permissions.zcml
eea/pdf/profiles.zcml
eea/pdf/skins.zcml
eea/pdf/utils.py
eea/pdf/version.txt
eea/pdf/Extensions/install.py
eea/pdf/browser/__init__.py
eea/pdf/browser/configure.zcml
eea/pdf/browser/interfaces.py
eea/pdf/browser/app/__init__.py
eea/pdf/browser/app/download.py
eea/pdf/browser/app/theme.py
eea/pdf/browser/app/tool.py
eea/pdf/browser/app/viewlet.py
eea/pdf/browser/css/view.css
eea/pdf/browser/img/download-pdf.png
eea/pdf/browser/img/email-pdf.png
eea/pdf/browser/img/icon.png
eea/pdf/browser/js/view.js
eea/pdf/browser/zpt/download.pt
eea/pdf/browser/zpt/theme.pt
eea/pdf/browser/zpt/tool.pt
eea/pdf/browser/zpt/viewlet.pt
eea/pdf/cache/__init__.py
eea/pdf/cache/behavior.py
eea/pdf/cache/cache.py
eea/pdf/cache/configure.zcml
eea/pdf/cache/nocache.py
eea/pdf/content/__init__.py
eea/pdf/content/configure.zcml
eea/pdf/content/interfaces.py
eea/pdf/content/theme.py
eea/pdf/content/tool.png
eea/pdf/content/tool.py
eea/pdf/events/__init__.py
eea/pdf/events/async.py
eea/pdf/events/configure.zcml
eea/pdf/events/interfaces.py
eea/pdf/events/subscribers.py
eea/pdf/events/sync.py
eea/pdf/exportimport/__init__.py
eea/pdf/exportimport/configure.zcml
eea/pdf/exportimport/exportimport.txt
eea/pdf/exportimport/theme.py
eea/pdf/exportimport/tool.py
eea/pdf/locales/eea.pot
eea/pdf/locales/update.sh
eea/pdf/locales/bg/LC_MESSAGES/eea.po
eea/pdf/locales/cs/LC_MESSAGES/eea.po
eea/pdf/locales/da/LC_MESSAGES/eea.po
eea/pdf/locales/de/LC_MESSAGES/eea.po
eea/pdf/locales/el/LC_MESSAGES/eea.po
eea/pdf/locales/en/LC_MESSAGES/eea.po
eea/pdf/locales/es/LC_MESSAGES/eea.po
eea/pdf/locales/et/LC_MESSAGES/eea.po
eea/pdf/locales/eu/LC_MESSAGES/eea.po
eea/pdf/locales/fi/LC_MESSAGES/eea.po
eea/pdf/locales/fr/LC_MESSAGES/eea.po
